project_info/__init__.py
project_info/context_processors.py
skip_django_project_info-1.0.2.1.dist-info/LICENSE
skip_django_project_info-1.0.2.1.dist-info/METADATA
skip_django_project_info-1.0.2.1.dist-info/WHEEL
skip_django_project_info-1.0.2.1.dist-info/top_level.txt
skip_django_project_info-1.0.2.1.dist-info/RECORD
