Metadata-Version: 2.1
Name: skip-django-project-info
Version: 1.0.2.1
Summary: A small plugin which takes a configuration (like Bower or npm) and it provides data via contextprocessors.
Home-page: https://github.com/skip-pay/django-project-info
Author: Lukas Rychtecky
Author-email: lukas.rychtecky@gmail.com
License: MIT
Keywords: django,project-info
License-File: LICENSE
Requires-Dist: django (>=1.11)
